{
  "id": "Object/isExtensible",
  "title": "Object.isExtensible()",
  "description": "## 语法",
  "source": "@site/docs/Object/Object.isExtensible.md",
  "permalink": "/docs/Object/isExtensible",
  "editUrl": "https://github.com/YanceyOfficial/javascript-apis/tree/master/docs/Object/Object.isExtensible.md",
  "lastUpdatedBy": "YanceyOfficial",
  "lastUpdatedAt": 1586254669,
  "sidebar": "ecmascript",
  "previous": {
    "title": "Object.freeze()",
    "permalink": "/docs/Object/freeze"
  },
  "next": {
    "title": "Object.isSealed()",
    "permalink": "/docs/Object/isSealed"
  }
}